filebrowse/__init__.py
filebrowse/filebrowse.py
FileBrowse-0.1.1.dist-info/LICENSE.txt
FileBrowse-0.1.1.dist-info/METADATA
FileBrowse-0.1.1.dist-info/WHEEL
FileBrowse-0.1.1.dist-info/top_level.txt
FileBrowse-0.1.1.dist-info/RECORD
