Metadata-Version: 2.1
Name: FileBrowse
Version: 0.1.1
Summary: A simple library to browse and select files without creating a GUI.
Home-page: https://github.com/jgera/filebrowse
Author: Jatin Gera
Author-email: gera.jatin@gmail.com
License: MIT
Classifier: Development Status :: 3 - Alpha
Classifier: Intended Audience :: Developers
Classifier: License :: OSI Approved :: MIT License
Classifier: Programming Language :: Python :: 3
Classifier: Programming Language :: Python :: 3.6
Classifier: Programming Language :: Python :: 3.7
Classifier: Programming Language :: Python :: 3.8
Classifier: Programming Language :: Python :: 3.9
Requires-Python: >=3.6
License-File: LICENSE.txt
